serpent_serve/__init__.py
serpent_serve/serpent.proto
serpent_serve/serpent_pb2.py
serpent_serve/serpent_pb2.pyi
serpent_serve/serpent_pb2_grpc.py
serpent_serve-0.1.1.dist-info/LICENSE
serpent_serve-0.1.1.dist-info/METADATA
serpent_serve-0.1.1.dist-info/WHEEL
serpent_serve-0.1.1.dist-info/RECORD
