Metadata-Version: 2.3
Name: serpent-serve
Version: 0.1.1
Summary: A Python gRPC wrapper for classes
License: GPL-3.0-only
Author: Pavel Oborin
Author-email: oborin.p@gmail.com
Requires-Python: >=3.8
Classifier: License :: OSI Approved :: GNU General Public License v3 (GPLv3)
Classifier: Programming Language :: Python :: 3
Classifier: Programming Language :: Python :: 3.8
Classifier: Programming Language :: Python :: 3.9
Classifier: Programming Language :: Python :: 3.10
Classifier: Programming Language :: Python :: 3.11
Classifier: Programming Language :: Python :: 3.12
Classifier: Programming Language :: Python :: 3.13
Provides-Extra: dev
Requires-Dist: grpcio
Requires-Dist: grpcio-tools
Requires-Dist: protobuf
Requires-Dist: pytest ; extra == "dev"
Requires-Dist: tblib
Project-URL: Homepage, https://pypi.org/project/serpent-serve/
Project-URL: Repository, https://github.com/oborichkin/serpent-serve
